phovea_security_flask/__init__.py
phovea_security_flask/config.json
phovea_security_flask/dummy_store.py
phovea_security_flask/flask_login_impl.py
phovea_security_flask-9.0.0.dist-info/LICENSE
phovea_security_flask-9.0.0.dist-info/METADATA
phovea_security_flask-9.0.0.dist-info/WHEEL
phovea_security_flask-9.0.0.dist-info/entry_points.txt
phovea_security_flask-9.0.0.dist-info/top_level.txt
phovea_security_flask-9.0.0.dist-info/RECORD
