Metadata-Version: 2.1
Name: phovea-security-flask
Version: 9.0.0
Summary: UNKNOWN
Home-page: https://phovea.caleydo.org
Author: The Caleydo Team
Author-email: contact@caleydo.org
License: BSD-3-Clause
Platform: UNKNOWN
Classifier: Intended Audience :: Developers
Classifier: Operating System :: OS Independent
Classifier: License :: OSI Approved :: BSD License
Classifier: Programming Language :: Python
Classifier: Programming Language :: Python :: 3.7
License-File: LICENSE
Requires-Dist: flask-login (==0.5.0)
Requires-Dist: phovea-server (<8.0.0,>=7.2.0)
